setup.py
Prue1.egg-info/PKG-INFO
Prue1.egg-info/SOURCES.txt
Prue1.egg-info/dependency_links.txt
Prue1.egg-info/top_level.txt
pytransform/__init__.py