Metadata-Version: 1.0
Name: Prue1
Version: 0.0.3
Summary: Operaciones de 2 digitos
Home-page: UNKNOWN
Author: Wilbert Sanchez
Author-email: wilbertenriquechable522@gmail.com
License: MIT
Keywords: calculator
Platform: UNKNOWN
